chainstate/__init__.py
chainstate/chainstate.py
chainstate-0.1.8.dist-info/LICENSE
chainstate-0.1.8.dist-info/METADATA
chainstate-0.1.8.dist-info/WHEEL
chainstate-0.1.8.dist-info/RECORD
