Metadata-Version: 2.1
Name: chainstate
Version: 0.1.8
Summary: A simple state chain library for Python
Author: Magnus Friberg
Author-email: magnus.uno.friberg@gmail.com
Requires-Python: >=3.8,<4.0
Classifier: Programming Language :: Python :: 3
Classifier: Programming Language :: Python :: 3.8
Classifier: Programming Language :: Python :: 3.9
Classifier: Programming Language :: Python :: 3.10
Classifier: Programming Language :: Python :: 3.11
Classifier: Programming Language :: Python :: 3.12
Classifier: Programming Language :: Python :: 3.13
